SimfPythonGUI/AboutDialog.ui
SimfPythonGUI/MainWindow.ui
SimfPythonGUI/PasswordDialog.ui
SimfPythonGUI/SettingsDialog.ui
SimfPythonGUI/VERSION
SimfPythonGUI/__init__.py
SimfPythonGUI/about.py
SimfPythonGUI/config.py
SimfPythonGUI/filehandlers.py
SimfPythonGUI/guientry.py
SimfPythonGUI/main.py
SimfPythonGUI/sudo.py
SimfPythonGUI-1.0.0b2.data/data/LICENSE.md
simf-python-gui/AboutDialog.ui
simf-python-gui/MainWindow.ui
simf-python-gui/PasswordDialog.ui
simf-python-gui/SettingsDialog.ui
simf-python-gui/__init__.py
simf-python-gui/about.py
simf-python-gui/config.py
simf-python-gui/filehandlers.py
simf-python-gui/main.py
simf-python-gui/sudo.py
SimfPythonGUI-1.0.0b2.dist-info/LICENSE.md
SimfPythonGUI-1.0.0b2.dist-info/METADATA
SimfPythonGUI-1.0.0b2.dist-info/WHEEL
SimfPythonGUI-1.0.0b2.dist-info/entry_points.txt
SimfPythonGUI-1.0.0b2.dist-info/top_level.txt
SimfPythonGUI-1.0.0b2.dist-info/RECORD
