Metadata-Version: 2.1
Name: SimfPythonGUI
Version: 1.0.0b2
Summary: A GUI controller for the closed source SIMF camera capture utility
Home-page: https://git.nclf.net/SIMF/simf-python-gui
Author: A.J. Fite, Sara Kipps
Author-email: me@ajfite.com, skipps@calpoly.edu
License: MIT
Platform: UNKNOWN
Classifier: Programming Language :: Python :: 3
Classifier: License :: OSI Approved :: MIT License
Classifier: Operating System :: OS Independent
Requires-Dist: PyQt5
Requires-Dist: watchdog
